
{"items":[{"name":"YW.CREDENTIAL_MANAGER","href":"api/YW.CREDENTIAL_MANAGER.html","topicHref":"api/YW.CREDENTIAL_MANAGER.html","topicUid":"YW.CREDENTIAL_MANAGER","items":[{"name":"CredentialManager","href":"api/YW.CREDENTIAL_MANAGER.CredentialManager.html","topicHref":"api/YW.CREDENTIAL_MANAGER.CredentialManager.html","topicUid":"YW.CREDENTIAL_MANAGER.CredentialManager"}]},{"name":"YW.CREDENTIAL_MANAGER.FACT","href":"api/YW.CREDENTIAL_MANAGER.FACT.html","topicHref":"api/YW.CREDENTIAL_MANAGER.FACT.html","topicUid":"YW.CREDENTIAL_MANAGER.FACT","items":[{"name":"CredentialManagerFact","href":"api/YW.CREDENTIAL_MANAGER.FACT.CredentialManagerFact.html","topicHref":"api/YW.CREDENTIAL_MANAGER.FACT.CredentialManagerFact.html","topicUid":"YW.CREDENTIAL_MANAGER.FACT.CredentialManagerFact"}]},{"name":"YW.CREDENTIAL_MANAGER.MacOS","href":"api/YW.CREDENTIAL_MANAGER.MacOS.html","topicHref":"api/YW.CREDENTIAL_MANAGER.MacOS.html","topicUid":"YW.CREDENTIAL_MANAGER.MacOS","items":[{"name":"KeyChainManager","href":"api/YW.CREDENTIAL_MANAGER.MacOS.KeyChainManager.html","topicHref":"api/YW.CREDENTIAL_MANAGER.MacOS.KeyChainManager.html","topicUid":"YW.CREDENTIAL_MANAGER.MacOS.KeyChainManager"}]}],"memberLayout":"SamePage","pdf":false}
